stichotrope/__init__.py
stichotrope/export.py
stichotrope/profiler.py
stichotrope/py.typed
stichotrope/timing.py
stichotrope/types.py
stichotrope-0.2.0.dist-info/licenses/LICENSE
stichotrope-0.2.0.dist-info/METADATA
stichotrope-0.2.0.dist-info/WHEEL
stichotrope-0.2.0.dist-info/top_level.txt
stichotrope-0.2.0.dist-info/RECORD
