Metadata-Version: 2.4
Name: stichotrope
Version: 0.2.0
Summary: Python profiling library with block-level profiling and multi-track organization
Author-email: Eliott Jacopin <eliott.jacopin@riken.jp>
License: AGPL-3.0-or-later
Project-URL: Homepage, https://github.com/LittleCoinCoin/stichotrope
Project-URL: Repository, https://github.com/LittleCoinCoin/stichotrope
Project-URL: Issues, https://github.com/LittleCoinCoin/stichotrope/issues
Keywords: profiling,performance,benchmarking,instrumentation,profiler
Classifier: Development Status :: 2 - Pre-Alpha
Classifier: Intended Audience :: Developers
Classifier: License :: OSI Approved :: GNU Affero General Public License v3 or later (AGPLv3+)
Classifier: Programming Language :: Python :: 3
Classifier: Programming Language :: Python :: 3.9
Classifier: Programming Language :: Python :: 3.10
Classifier: Programming Language :: Python :: 3.11
Classifier: Programming Language :: Python :: 3.12
Classifier: Programming Language :: Python :: 3.13
Classifier: Topic :: Software Development :: Libraries :: Python Modules
Classifier: Topic :: Software Development :: Testing
Classifier: Topic :: System :: Benchmark
Requires-Python: >=3.9
License-File: LICENSE
Requires-Dist: tomli>=2.0.0; python_version < "3.11"
Requires-Dist: tomli-w>=1.0.0
Provides-Extra: dev
Requires-Dist: python-semantic-release>=8.0.0; extra == "dev"
Requires-Dist: pytest>=7.0.0; extra == "dev"
Requires-Dist: pytest-cov>=4.0.0; extra == "dev"
Requires-Dist: pytest-timeout>=2.1.0; extra == "dev"
Requires-Dist: psutil>=5.9.0; extra == "dev"
Requires-Dist: scipy>=1.11.0; extra == "dev"
Requires-Dist: matplotlib>=3.8.0; extra == "dev"
Requires-Dist: black>=23.0.0; extra == "dev"
Requires-Dist: ruff>=0.1.0; extra == "dev"
Requires-Dist: mypy>=1.0.0; extra == "dev"
Provides-Extra: docs
Requires-Dist: mkdocs>=1.5.0; extra == "docs"
Requires-Dist: mkdocstrings[python]>=0.24.0; extra == "docs"
Requires-Dist: mkdocs-material>=9.5.0; extra == "docs"
Requires-Dist: mkdocs-print-site-plugin>=2.8; extra == "docs"
Dynamic: license-file
